{
  "indexes": [
    {
      "collectionGroup": "emergencies",
      "queryScope": "COLLECTION",
      "fields": [
        { "fieldPath": "victimId", "order": "ASCENDING" },
        { "fieldPath": "status", "order": "ASCENDING" },
        { "fieldPath": "createdAt", "order": "DESCENDING" }
      ]
    },
    {
      "collectionGroup": "emergencies",
      "queryScope": "COLLECTION",
      "fields": [
        { "fieldPath": "status", "order": "ASCENDING" },
        { "fieldPath": "notifiedResponders", "arrayConfig": "CONTAINS" },
        { "fieldPath": "createdAt", "order": "DESCENDING" }
      ]
    },
    {
      "collectionGroup": "responder_locations",
      "queryScope": "COLLECTION",
      "fields": [
        { "fieldPath": "isActive", "order": "ASCENDING" },
        { "fieldPath": "position.geohash", "order": "ASCENDING" }
      ]
    },
    {
      "collectionGroup": "chat",
      "queryScope": "COLLECTION",
      "fields": [
        { "fieldPath": "timestamp", "order": "ASCENDING" }
      ]
    },
    {
      "collectionGroup": "chat",
      "queryScope": "COLLECTION",
      "fields": [
        { "fieldPath": "read", "order": "ASCENDING" },
        { "fieldPath": "senderId", "order": "ASCENDING" }
      ]
    }
  ],
  "fieldOverrides": []
}
